dilithium_python-0.1.0.dist-info/METADATA
dilithium_python-0.1.0.dist-info/WHEEL
dilithium_python/__init__.py
dilithium_python/__init__.pyi
dilithium_python/py.typed
dilithium_python/dilithium_python.pyd
dilithium_python-0.1.0.dist-info/RECORD
