Metadata-Version: 2.4
Name: dilithium_python
Version: 0.1.0
Summary: Python bindings for Dilithium post-quantum signatures
Author: konstantin Gorshkov <kostya_gorshkov_06@vk.com>
Author-email: konstantin Gorshkov <kostya_gorshkov_06@vk.com>
License: MIT
Project-URL: Source Code, https://github.com/kostya2023/dilithium-python
